netbox_storage/__init__.py
netbox_storage/filtersets.py
netbox_storage/forms.py
netbox_storage/models.py
netbox_storage/navigation.py
netbox_storage/tables.py
netbox_storage/template_content.py
netbox_storage/urls.py
netbox_storage/views.py
netbox_storage/api/__init__.py
netbox_storage/api/serializers.py
netbox_storage/api/urls.py
netbox_storage/api/views.py
netbox_storage/migrations/0001_initial.py
netbox_storage/migrations/__init__.py
netbox_storage/templates/netbox_storage/datastore.html
netbox_storage/templates/netbox_storage/lun.html
netbox_storage/templates/netbox_storage/storagepool.html
netbox_storage/templates/netbox_storage/storagesession.html
netbox_storage/templates/netbox_storage/vm_vmdk_extend.html
netbox_storage/templates/netbox_storage/vmdk.html
netbox_storage_plugin-0.8.0.dist-info/licenses/LICENSE
netbox_storage_plugin-0.8.0.dist-info/METADATA
netbox_storage_plugin-0.8.0.dist-info/WHEEL
netbox_storage_plugin-0.8.0.dist-info/top_level.txt
netbox_storage_plugin-0.8.0.dist-info/RECORD
