Metadata-Version: 2.4
Name: netbox-storage-plugin
Version: 0.8.0
Summary: NetBox storage plugin
Home-page: https://github.com/viroge/netbox-storage
Author: Gabor Somogyvari
Keywords: netbox,netbox-plugin
Classifier: Programming Language :: Python :: 3
Classifier: License :: OSI Approved :: Apache Software License
Classifier: Development Status :: 4 - Beta
License-File: LICENSE
Dynamic: author
Dynamic: classifier
Dynamic: description
Dynamic: description-content-type
Dynamic: home-page
Dynamic: keywords
Dynamic: license-file
Dynamic: summary
